spherical_tools/__init__.py
spherical_tools/_core.py
spherical_tools/_vendor/slerp.py
spherical_tools/wrappers/__init__.py
spherical_tools/wrappers/conversion.py
spherical_tools/wrappers/decorators.py
spherical_tools/wrappers/geodetic.py
spherical_tools-0.2.0.dist-info/licenses/LICENSE
spherical_tools-0.2.0.dist-info/METADATA
spherical_tools-0.2.0.dist-info/WHEEL
spherical_tools-0.2.0.dist-info/top_level.txt
spherical_tools-0.2.0.dist-info/RECORD
