Metadata-Version: 2.4
Name: spherical-tools
Version: 0.2.0
Summary: Utilities for working with spherical geometry
Author-email: Tom New <tomnewtonnew@gmail.com>
License: # MIT License
Project-URL: Homepage, https://github.com/tom-new/spherical-tools
Keywords: geoscience,coordinates,spherical,cartesian,geometry
Requires-Python: >=3.10
License-File: LICENSE
Requires-Dist: numpy
Provides-Extra: dev
Requires-Dist: pytest<9,>=8; extra == "dev"
Requires-Dist: pytest-cov<6,>=5; extra == "dev"
Requires-Dist: black<26,>=25.1; extra == "dev"
Dynamic: license-file
